neo/__init__.py
neo/__main__.py
neo/adapters.py
neo/algorithm_design.py
neo/cli.py
neo/config.py
neo/constraint_verification.py
neo/construct.py
neo/context_gatherer.py
neo/exemplar_index.py
neo/input_templates.py
neo/lm_logger.py
neo/load_env.py
neo/math_utils.py
neo/parsers.py
neo/pattern_extraction.py
neo/persistent_reasoning.py
neo/program_loader.py
neo/repair_loop.py
neo/schemas.py
neo/self_correction.py
neo/static_analysis.py
neo/stdin_wrapper.py
neo/storage.py
neo/storage_interface.py
neo/structured_parser.py
neo/config/beats/neo_matrix.yaml
neo_reasoner-0.8.0.dist-info/METADATA
neo_reasoner-0.8.0.dist-info/WHEEL
neo_reasoner-0.8.0.dist-info/entry_points.txt
neo_reasoner-0.8.0.dist-info/licenses/LICENSE
neo_reasoner-0.8.0.dist-info/RECORD
