Metadata-Version: 2.4
Name: neo-reasoner
Version: 0.8.0
Summary: A self-improving code reasoning engine with persistent semantic memory
Project-URL: Homepage, https://github.com/Parslee-ai/neo
Project-URL: Documentation, https://github.com/Parslee-ai/neo/blob/main/README.md
Project-URL: Repository, https://github.com/Parslee-ai/neo
Project-URL: Issues, https://github.com/Parslee-ai/neo/issues
Project-URL: Changelog, https://github.com/Parslee-ai/neo/blob/main/CHANGELOG.md
Author-email: Parslee AI <hello@parslee.ai>
License: Apache-2.0
License-File: LICENSE
Keywords: ai,cli,code-generation,embeddings,llm,reasoning,semantic-memory
Classifier: Development Status :: 3 - Alpha
Classifier: Intended Audience :: Developers
Classifier: License :: OSI Approved :: Apache Software License
Classifier: Operating System :: OS Independent
Classifier: Programming Language :: Python :: 3
Classifier: Programming Language :: Python :: 3.9
Classifier: Programming Language :: Python :: 3.10
Classifier: Programming Language :: Python :: 3.11
Classifier: Programming Language :: Python :: 3.12
Classifier: Programming Language :: Python :: 3.13
Classifier: Topic :: Scientific/Engineering :: Artificial Intelligence
Classifier: Topic :: Software Development :: Libraries :: Python Modules
Requires-Python: >=3.9
Requires-Dist: datasketch>=1.6.0
Requires-Dist: faiss-cpu>=1.7.0
Requires-Dist: fastembed>=0.3.0
Requires-Dist: numpy>=1.24.0
Requires-Dist: scikit-learn>=1.3.0
Provides-Extra: all
Requires-Dist: anthropic>=0.21.0; extra == 'all'
Requires-Dist: google-generativeai>=0.3.0; extra == 'all'
Requires-Dist: openai>=1.0.0; extra == 'all'
Requires-Dist: requests>=2.31.0; extra == 'all'
Provides-Extra: anthropic
Requires-Dist: anthropic>=0.21.0; extra == 'anthropic'
Provides-Extra: dev
Requires-Dist: black>=23.0.0; extra == 'dev'
Requires-Dist: mypy>=1.0.0; extra == 'dev'
Requires-Dist: pytest>=7.0.0; extra == 'dev'
Requires-Dist: ruff>=0.1.0; extra == 'dev'
Provides-Extra: google
Requires-Dist: google-generativeai>=0.3.0; extra == 'google'
Provides-Extra: ollama
Requires-Dist: requests>=2.31.0; extra == 'ollama'
Provides-Extra: openai
Requires-Dist: openai>=1.0.0; extra == 'openai'
